{"type":"FeatureCollection","features":[{"type":"Feature","geometry":{"type":"Point","coordinates":[-80.9319,36.5749,0]},"properties":{"name":"Crabill prospect","description":"<p>Data source: <a href=\"http://mrdata.usgs.gov/asbestos/\">Asbestos mines, prospects, and occurrences in the US</a></p><p>[<a href=\"http://mrdata.usgs.gov/asbestos/show.php?labno=681\">All data for record 681</a>]</p><table border='1' padding='3' cellspacing='0'></table>"}}]}