{"type":"FeatureCollection","features":[{"type":"Feature","geometry":{"type":"Point","coordinates":[-78.426,38.603,0]},"properties":{"name":"Ida copper mine","description":"<p>Data source: <a href=\"http://mrdata.usgs.gov/asbestos/\">Asbestos mines, prospects, and occurrences in the US</a></p><p>[<a href=\"http://mrdata.usgs.gov/asbestos/show.php?labno=699\">All data for record 699</a>]</p><table border='1' padding='3' cellspacing='0'></table>"}}]}