{"type":"FeatureCollection","features":[{"type":"Feature","geometry":{"type":"Point","coordinates":[-79.043056,38.236111,0]},"properties":{"name":7404,"description":"<p>Data source: <a href=\"http://mrdata.usgs.gov/geochron/\">National Geochronological Database</a></p><p>[<a href=\"http://mrdata.usgs.gov/geochron/show.php?labno=7404\">All data for record 7404</a>]</p><table border='1' padding='3' cellspacing='0'><tr valign='top'><th align='right' bgcolor='#ddffee' title='General type of material sampled or geographic feature from which the sample was taken.'>Source of sample</th><td>Outcrop or artificial surface exposure</td></tr><tr valign='top'><th align='right' bgcolor='#ddffee' title='Lithologic terms describing the sample'>Rock name</th><td>Teschenite</td></tr><tr valign='top'><th align='right' bgcolor='#ddffee' title='Further description of the sampled material, often includes a geologic unit or structural element within the unit.'>Description</th><td>ALKALIC DIKE COMPLEX</td></tr><tr valign='top'><th align='right' bgcolor='#ddffee' title='Name of the person who compiled the data.'>Compiler name</th><td>Marvin, R.F.</td></tr><tr valign='top'><th align='right' bgcolor='#ddffee' title='Date record information was compiled, as year and month formatted as YYYY MM'>Date compiled</th><td>1980 05</td></tr></table>"}},{"type":"Feature","geometry":{"type":"Point","coordinates":[-79.033333,38.083333,0]},"properties":{"name":17477,"description":"<p>Data source: <a href=\"http://mrdata.usgs.gov/geochron/\">National Geochronological Database</a></p><p>[<a href=\"http://mrdata.usgs.gov/geochron/show.php?labno=17477\">All data for record 17477</a>]</p><table border='1' padding='3' cellspacing='0'><tr valign='top'><th align='right' bgcolor='#ddffee' title='General type of material sampled or geographic feature from which the sample was taken.'>Source of sample</th><td>Outcrop or artificial surface exposure</td></tr><tr valign='top'><th align='right' bgcolor='#ddffee' title='Lithologic terms describing the sample'>Rock name</th><td>Basalt</td></tr><tr valign='top'><th align='right' bgcolor='#ddffee' title='Further description of the sampled material, often includes a geologic unit or structural element within the unit.'>Description</th><td>Most flows are qtz-normative tholeiites except sample B which is olv-normative samples A3,A5,B,G,LI,L2,Q,T,WO,Ci, and:Ep are from more shisstose parts of the flows and were used to define the 450 Ma isochron. All  others were used to define the 570 Ma iso</td></tr><tr valign='top'><th align='right' bgcolor='#ddffee' title='Name of the person who compiled the data.'>Compiler name</th><td>Roland, R.</td></tr><tr valign='top'><th align='right' bgcolor='#ddffee' title='Date record information was compiled, as year and month formatted as YYYY MM'>Date compiled</th><td>1993 08</td></tr></table>"}}]}