{"type":"FeatureCollection","features":[{"type":"Feature","geometry":{"type":"Point","coordinates":[-78.291,38.79,0]},"properties":{"name":"Empire vein copper prospects","description":"<p>Data source: <a href=\"http://mrdata.usgs.gov/asbestos/\">Asbestos mines, prospects, and occurrences in the US</a></p><p>[<a href=\"http://mrdata.usgs.gov/asbestos/show.php?labno=700\">All data for record 700</a>]</p><table border='1' padding='3' cellspacing='0'></table>"}}]}