{"type":"FeatureCollection","features":[{"type":"Feature","geometry":{"type":"Point","coordinates":[-79.165278,37.85,0]},"properties":{"name":14504,"description":"<p>Data source: <a href=\"http://mrdata.usgs.gov/geochron/\">National Geochronological Database</a></p><p>[<a href=\"http://mrdata.usgs.gov/geochron/show.php?labno=14504\">All data for record 14504</a>]</p><table border='1' padding='3' cellspacing='0'><tr valign='top'><th align='right' bgcolor='#ddffee' title='General type of material sampled or geographic feature from which the sample was taken.'>Source of sample</th><td>Quarry</td></tr><tr valign='top'><th align='right' bgcolor='#ddffee' title='Lithologic terms describing the sample'>Rock name</th><td>Greisen</td></tr><tr valign='top'><th align='right' bgcolor='#ddffee' title='Further description of the sampled material, often includes a geologic unit or structural element within the unit.'>Description</th><td>A QUARTZ-MUSCOVITE GREISEN WITH MINOR CASSITERITE; LARGE, RANDONLY ORIENTED BOOKS OF MUSCOVITE</td></tr><tr valign='top'><th align='right' bgcolor='#ddffee' title='Name of the person who compiled the data.'>Compiler name</th><td>Marvin, R.F.</td></tr><tr valign='top'><th align='right' bgcolor='#ddffee' title='Date record information was compiled, as year and month formatted as YYYY MM'>Date compiled</th><td>1984 05</td></tr></table>"}},{"type":"Feature","geometry":{"type":"Point","coordinates":[-79.165278,37.85,0]},"properties":{"name":14505,"description":"<p>Data source: <a href=\"http://mrdata.usgs.gov/geochron/\">National Geochronological Database</a></p><p>[<a href=\"http://mrdata.usgs.gov/geochron/show.php?labno=14505\">All data for record 14505</a>]</p><table border='1' padding='3' cellspacing='0'><tr valign='top'><th align='right' bgcolor='#ddffee' title='General type of material sampled or geographic feature from which the sample was taken.'>Source of sample</th><td>Quarry</td></tr><tr valign='top'><th align='right' bgcolor='#ddffee' title='Lithologic terms describing the sample'>Rock name</th><td>Greisen</td></tr><tr valign='top'><th align='right' bgcolor='#ddffee' title='Further description of the sampled material, often includes a geologic unit or structural element within the unit.'>Description</th><td>FINE-GRAINED QUARTZ-MUSCOVITE GREISEN</td></tr><tr valign='top'><th align='right' bgcolor='#ddffee' title='Name of the person who compiled the data.'>Compiler name</th><td>Marvin, R.F.</td></tr><tr valign='top'><th align='right' bgcolor='#ddffee' title='Date record information was compiled, as year and month formatted as YYYY MM'>Date compiled</th><td>1984 05</td></tr></table>"}}]}