{"type":"FeatureCollection","features":[{"type":"Feature","geometry":{"type":"Point","coordinates":[-79.437222,37.318889,0]},"properties":{"name":5330,"description":"<p>Data source: <a href=\"http://mrdata.usgs.gov/geochron/\">National Geochronological Database</a></p><p>[<a href=\"http://mrdata.usgs.gov/geochron/show.php?labno=5330\">All data for record 5330</a>]</p><table border='1' padding='3' cellspacing='0'><tr valign='top'><th align='right' bgcolor='#ddffee' title='General type of material sampled or geographic feature from which the sample was taken.'>Source of sample</th><td>Outcrop or artificial surface exposure</td></tr><tr valign='top'><th align='right' bgcolor='#ddffee' title='Lithologic terms describing the sample'>Rock name</th><td>Gneiss</td></tr><tr valign='top'><th align='right' bgcolor='#ddffee' title='Further description of the sampled material, often includes a geologic unit or structural element within the unit.'>Description</th><td>FINE-GRAINED BANDED LYNCHBURG GNEISS COMPOSED OF QUARTZ, BIOTITE, MINOR PLAGIOCLASE, AND ACCESSORY SPHENE, APATITE, GARNET, ZOISITE, EPIDOTE, AND CLINOZOISITE</td></tr><tr valign='top'><th align='right' bgcolor='#ddffee' title='Name of the person who compiled the data.'>Compiler name</th><td>Godoy, M.M.</td></tr><tr valign='top'><th align='right' bgcolor='#ddffee' title='Date record information was compiled, as year and month formatted as YYYY MM'>Date compiled</th><td>1979 03</td></tr></table>"}},{"type":"Feature","geometry":{"type":"Point","coordinates":[-79.553333,37.493333,0]},"properties":{"name":6198,"description":"<p>Data source: <a href=\"http://mrdata.usgs.gov/geochron/\">National Geochronological Database</a></p><p>[<a href=\"http://mrdata.usgs.gov/geochron/show.php?labno=6198\">All data for record 6198</a>]</p><table border='1' padding='3' cellspacing='0'><tr valign='top'><th align='right' bgcolor='#ddffee' title='General type of material sampled or geographic feature from which the sample was taken.'>Source of sample</th><td>Outcrop or artificial surface exposure</td></tr><tr valign='top'><th align='right' bgcolor='#ddffee' title='Lithologic terms describing the sample'>Rock name</th><td>Gneiss</td></tr><tr valign='top'><th align='right' bgcolor='#ddffee' title='Further description of the sampled material, often includes a geologic unit or structural element within the unit.'>Description</th><td>GRANITIC GNEISS</td></tr><tr valign='top'><th align='right' bgcolor='#ddffee' title='Name of the person who compiled the data.'>Compiler name</th><td>Marvin, R.F.</td></tr><tr valign='top'><th align='right' bgcolor='#ddffee' title='Date record information was compiled, as year and month formatted as YYYY MM'>Date compiled</th><td>1979 10</td></tr></table>"}}]}