{"type":"FeatureCollection","features":[{"type":"Feature","geometry":{"type":"Point","coordinates":[-77.4136,36.66037,0]},"properties":{"name":"Al Clary & Son Pit No. 1","description":"<p>Record <a href=\"http://mrdata.usgs.gov/mrds/show.php?labno=10179596\">10179596</a></p><p>Data source: <a href=\"http://mrdata.usgs.gov/mrds/\">Mineral Resources Data System</a></p><table border='1' padding='3' cellspacing='0'><tr valign='top'><th align='right' bgcolor='#ddffee'>oper_type</th><td>Surface</td></tr><tr valign='top'><th align='right' bgcolor='#ddffee'>dev_stat</th><td>Producer</td></tr><tr valign='top'><th align='right' bgcolor='#ddffee'>ore</th><td></td></tr><tr valign='top'><th align='right' bgcolor='#ddffee'>model</th><td></td></tr><tr valign='top'><th align='right' bgcolor='#ddffee'>commod1</th><td>Sand and Gravel, Construction</td></tr><tr valign='top'><th align='right' bgcolor='#ddffee'>commod2</th><td></td></tr><tr valign='top'><th align='right' bgcolor='#ddffee'>commod3</th><td></td></tr></table>"}},{"type":"Feature","geometry":{"type":"Point","coordinates":[-77.19109,36.56537,0]},"properties":{"name":"Melvin E. Mann Sand Pit","description":"<p>Record <a href=\"http://mrdata.usgs.gov/mrds/show.php?labno=10183012\">10183012</a></p><p>Data source: <a href=\"http://mrdata.usgs.gov/mrds/\">Mineral Resources Data System</a></p><table border='1' padding='3' cellspacing='0'><tr valign='top'><th align='right' bgcolor='#ddffee'>oper_type</th><td>Offshore</td></tr><tr valign='top'><th align='right' bgcolor='#ddffee'>dev_stat</th><td>Producer</td></tr><tr valign='top'><th align='right' bgcolor='#ddffee'>ore</th><td></td></tr><tr valign='top'><th align='right' bgcolor='#ddffee'>model</th><td></td></tr><tr valign='top'><th align='right' bgcolor='#ddffee'>commod1</th><td>Sand and Gravel, Construction</td></tr><tr valign='top'><th align='right' bgcolor='#ddffee'>commod2</th><td></td></tr><tr valign='top'><th align='right' bgcolor='#ddffee'>commod3</th><td></td></tr></table>"}}]}